emlvp/VERSION.txt
emlvp/__init__.py
emlvp/changelog.md
emlvp/dereferencer.py
emlvp/emlvp_cli.py
emlvp/exceptions.py
emlvp/normalizer.py
emlvp/parser.py
emlvp/unicode_inspector.py
emlvp/validator.py
emlvp/schemas/EML2.1.0/eml-access.xsd
emlvp/schemas/EML2.1.0/eml-attribute.xsd
emlvp/schemas/EML2.1.0/eml-constraint.xsd
emlvp/schemas/EML2.1.0/eml-coverage.xsd
emlvp/schemas/EML2.1.0/eml-dataTable.xsd
emlvp/schemas/EML2.1.0/eml-dataset.xsd
emlvp/schemas/EML2.1.0/eml-documentation.xsd
emlvp/schemas/EML2.1.0/eml-entity.xsd
emlvp/schemas/EML2.1.0/eml-literature.xsd
emlvp/schemas/EML2.1.0/eml-methods.xsd
emlvp/schemas/EML2.1.0/eml-party.xsd
emlvp/schemas/EML2.1.0/eml-physical.xsd
emlvp/schemas/EML2.1.0/eml-project.xsd
emlvp/schemas/EML2.1.0/eml-protocol.xsd
emlvp/schemas/EML2.1.0/eml-resource.xsd
emlvp/schemas/EML2.1.0/eml-software.xsd
emlvp/schemas/EML2.1.0/eml-spatialRaster.xsd
emlvp/schemas/EML2.1.0/eml-spatialReference.xsd
emlvp/schemas/EML2.1.0/eml-spatialReferenceDictionary.xml
emlvp/schemas/EML2.1.0/eml-spatialVector.xsd
emlvp/schemas/EML2.1.0/eml-storedProcedure.xsd
emlvp/schemas/EML2.1.0/eml-text.xsd
emlvp/schemas/EML2.1.0/eml-unitDictionary.xml
emlvp/schemas/EML2.1.0/eml-unitTypeDefinitions.xsd
emlvp/schemas/EML2.1.0/eml-view.xsd
emlvp/schemas/EML2.1.0/eml.xsd
emlvp/schemas/EML2.1.0/stmml.xsd
emlvp/schemas/EML2.1.1/eml-access.xsd
emlvp/schemas/EML2.1.1/eml-attribute.xsd
emlvp/schemas/EML2.1.1/eml-constraint.xsd
emlvp/schemas/EML2.1.1/eml-coverage.xsd
emlvp/schemas/EML2.1.1/eml-dataTable.xsd
emlvp/schemas/EML2.1.1/eml-dataset.xsd
emlvp/schemas/EML2.1.1/eml-documentation.xsd
emlvp/schemas/EML2.1.1/eml-entity.xsd
emlvp/schemas/EML2.1.1/eml-literature.xsd
emlvp/schemas/EML2.1.1/eml-methods.xsd
emlvp/schemas/EML2.1.1/eml-party.xsd
emlvp/schemas/EML2.1.1/eml-physical.xsd
emlvp/schemas/EML2.1.1/eml-project.xsd
emlvp/schemas/EML2.1.1/eml-protocol.xsd
emlvp/schemas/EML2.1.1/eml-resource.xsd
emlvp/schemas/EML2.1.1/eml-software.xsd
emlvp-1.2.7.dist-info/METADATA
emlvp-1.2.7.dist-info/WHEEL
emlvp-1.2.7.dist-info/entry_points.txt
emlvp-1.2.7.dist-info/licenses/LICENSE
emlvp-1.2.7.dist-info/RECORD
