Metadata-Version: 2.4
Name: EMLvp
Version: 1.2.7
Author-email: Mark Servilla <mark.servilla@gmail.com>
License:                                  Apache License
License-File: LICENSE
Requires-Python: <3.14,>=3.11
Requires-Dist: click<9,>=8.1.8
Requires-Dist: daiquiri<4,>=3.0.0
Requires-Dist: lxml<6,>=5.3.1
